{
  "months": {
    "ru": [
      "Январь",
      "Февраль",
      "Март",
      "Апрель ",
      "Май",
      "Июнь",
      "Июль",
      "Август",
      "Сентябрь",
      "Октябрь",
      "Ноябрь",
      "Декабрь"
    ],
    "eu": [
      "january",
      "february",
      "march",
      "april",
      "may",
      "june",
      "july",
      "august",
      "september",
      "october",
      "november",
      "december"
    ]
  },
  "todos": [
    {
      "months": {
        "monthRu": "Январь",
        "monthEu": "january",
        "day": 2
      },
      "text": "1313",
      "id": 1628236747124,
      "completed": false
    }
  ]
}